metalog_jax/__init__.py
metalog_jax/grid_search.py
metalog_jax/metalog.py
metalog_jax/utils.py
metalog_jax/base/__init__.py
metalog_jax/base/core.py
metalog_jax/base/data.py
metalog_jax/base/enums.py
metalog_jax/base/parameters.py
metalog_jax/regression/__init__.py
metalog_jax/regression/base.py
metalog_jax/regression/lasso.py
metalog_jax/regression/ols.py
metalog_jax-1.0.1.dist-info/licenses/LICENSE
metalog_jax-1.0.1.dist-info/METADATA
metalog_jax-1.0.1.dist-info/WHEEL
metalog_jax-1.0.1.dist-info/top_level.txt
metalog_jax-1.0.1.dist-info/RECORD
