Metadata-Version: 2.4
Name: metalog-jax
Version: 1.0.1
Summary: A JAX implementation of the Metalog distribution for flexible probability modeling.
Author: Travis Jefferies
Maintainer: Travis Jefferies
License-Expression: MIT
Keywords: jax,metalog,probability,distribution,quantile,statistics
Classifier: Development Status :: 4 - Beta
Classifier: Intended Audience :: Developers
Classifier: Intended Audience :: Science/Research
Classifier: Operating System :: OS Independent
Classifier: Programming Language :: Python :: 3
Classifier: Programming Language :: Python :: 3.11
Classifier: Topic :: Scientific/Engineering :: Mathematics
Classifier: Topic :: Scientific/Engineering :: Artificial Intelligence
Classifier: Typing :: Typed
Requires-Python: >=3.11
License-File: LICENSE
Requires-Dist: chex>=0.1.91
Requires-Dist: flax>=0.12.0
Requires-Dist: jax>=0.8.0
Requires-Dist: plotly>=6.4.0
Dynamic: license-file
